{
  "id": "5ab534f8710cef0014e63590",
  "title": "両声類",
  "created": 1521825030,
  "updated": 1521825269,
  "lines": [
    {
      "id": "5ab534f8710cef0014e63590",
      "text": "両声類",
      "userId": "59fb21121207900012774b17",
      "created": 1521825030,
      "updated": 1521825076
    },
    {
      "id": "5ab5350f774b17000000e7b9",
      "text": " 男性女性どちらの声も出せる人のこと",
      "userId": "59fb21121207900012774b17",
      "created": 1521825041,
      "updated": 1521825070
    },
    {
      "id": "5ab53529774b17000000e7ba",
      "text": "",
      "userId": "59fb21121207900012774b17",
      "created": 1521825066,
      "updated": 1521825066
    },
    {
      "id": "5ab53505774b17000000e7b6",
      "text": "参考",
      "userId": "59fb21121207900012774b17",
      "created": 1521825030,
      "updated": 1521825033
    },
    {
      "id": "5ab53507774b17000000e7b8",
      "text": " [http://dic.nicovideo.jp/a/%E4%B8%A1%E5%A3%B0%E9%A1%9E 両声類とは (リョウセイルイとは)  - ニコニコ大百科]",
      "userId": "59fb21121207900012774b17",
      "created": 1521825033,
      "updated": 1521825037
    },
    {
      "id": "5ab53586774b17000000e7bb",
      "text": "",
      "userId": "59fb21121207900012774b17",
      "created": 1521825159,
      "updated": 1521825159
    },
    {
      "id": "5ab53505774b17000000e7b7",
      "text": "なり方",
      "userId": "59fb21121207900012774b17",
      "created": 1521825030,
      "updated": 1521825162
    },
    {
      "id": "5ab535eb774b17000000e7be",
      "text": " [ふぇありす]さんの解説",
      "userId": "59fb21121207900012774b17",
      "created": 1521825260,
      "updated": 1521825268
    },
    {
      "id": "5ab53589774b17000000e7bd",
      "text": "  [http://www.nicovideo.jp/watch/sm32498567 【HTCvive+Unity】みんなもバーチャルアイドルになろう！　両声類紹介編 - ニコニコ動画]",
      "userId": "59fb21121207900012774b17",
      "created": 1521825162,
      "updated": 1521825269
    },
    {
      "id": "5ab53589774b17000000e7bc",
      "text": "",
      "userId": "59fb21121207900012774b17",
      "created": 1521825162,
      "updated": 1521825162
    }
  ]
}