{
  "id": "5ac3a2763b980a0014e9a2c5",
  "title": "いちから株式会社",
  "created": 1522770553,
  "updated": 1621238998,
  "lines": [
    {
      "id": "5ac3a2763b980a0014e9a2c5",
      "text": "いちから株式会社",
      "userId": "59fb21121207900012774b17",
      "created": 1522770553,
      "updated": 1522770553
    },
    {
      "id": "5cbc9388774b170000c16818",
      "text": "[https://gyazo.com/9232cbe608873155f4349f871dbf75ba]",
      "userId": "59fb21121207900012774b17",
      "created": 1555862408,
      "updated": 1555862408
    },
    {
      "id": "5ad205b2774b170000a02fb5",
      "text": "[https://gyazo.com/80df18c3cce2ab242b3a063f8fc24e46]",
      "userId": "59fb21121207900012774b17",
      "created": 1523713458,
      "updated": 1523713458
    },
    {
      "id": "60a224d0774b1700002c0099",
      "text": " 2021/5/17 社名変更により[ANYCOLOR株式会社]となる",
      "userId": "5a4296f4464d9800140db335",
      "created": 1621238992,
      "updated": 1621463868
    },
    {
      "id": "5ac3a277774b170000a4010f",
      "text": " [にじさんじ]を作っている会社",
      "userId": "59fb21121207900012774b17",
      "created": 1522770553,
      "updated": 1522770573
    },
    {
      "id": "5ad2058a774b170000a02fb2",
      "text": " 企業理念は「魔法のような技術で夢と幸せを提供する」",
      "userId": "59fb21121207900012774b17",
      "created": 1523713419,
      "updated": 1523713425
    },
    {
      "id": "5ad2057c774b170000a02fb1",
      "text": " https://www.ichikara.co.jp/",
      "userId": "59fb21121207900012774b17",
      "created": 1523713404,
      "updated": 1523713404
    },
    {
      "id": "5ac3a281774b170000a40112",
      "text": " 最年長社員は[いわなが]さん",
      "userId": "59fb21121207900012774b17",
      "created": 1522770562,
      "updated": 1526053179
    },
    {
      "id": "5af5b908774b170000d6623a",
      "text": "",
      "userId": "59fb21121207900012774b17",
      "created": 1526053179,
      "updated": 1526053179
    },
    {
      "id": "5df9b7d10db33500003c5209",
      "text": "関連事業",
      "userId": "5a4296f4464d9800140db335",
      "created": 1576646604,
      "updated": 1576646616
    },
    {
      "id": "5df9b7de0db33500003c520b",
      "text": "　[にじさんじ]",
      "userId": "5a4296f4464d9800140db335",
      "created": 1576646617,
      "updated": 1576646620
    },
    {
      "id": "5df9b7e20db33500003c520c",
      "text": "　[ユメノグラフィア]",
      "userId": "5a4296f4464d9800140db335",
      "created": 1576646621,
      "updated": 1576646628
    },
    {
      "id": "5df9b81c0db33500003c5211",
      "text": "　[にじさんじ台北]・[にじさんじ上海]（終了済み。[VEgo]へ移行）",
      "userId": "5a4296f4464d9800140db335",
      "created": 1576646679,
      "updated": 1576646718
    },
    {
      "id": "5df9b7f70db33500003c5210",
      "text": "　[VirtuaReal Project]",
      "userId": "5a4296f4464d9800140db335",
      "created": 1576646642,
      "updated": 1576646678
    },
    {
      "id": "5df9b7e90db33500003c520d",
      "text": "　[NIJISANJI ID]",
      "userId": "5a4296f4464d9800140db335",
      "created": 1576646628,
      "updated": 1577342002
    },
    {
      "id": "5df9b7f00db33500003c520e",
      "text": "　[NIJISANJI EN]",
      "userId": "5a4296f4464d9800140db335",
      "created": 1576646635,
      "updated": 1592819603
    },
    {
      "id": "5df9b7f20db33500003c520f",
      "text": "　[NIJISANJI KR]",
      "userId": "5a4296f4464d9800140db335",
      "created": 1576646637,
      "updated": 1576646640
    },
    {
      "id": "5e420ff90db3350000c7a0c7",
      "text": "　[SLEE]",
      "userId": "5a4296f4464d9800140db335",
      "created": 1581387769,
      "updated": 1581387770
    },
    {
      "id": "5df9b7d20db33500003c520a",
      "text": "",
      "userId": "5a4296f4464d9800140db335",
      "created": 1576646605,
      "updated": 1576646605
    },
    {
      "id": "5ac3a280774b170000a40111",
      "text": "#企業",
      "userId": "59fb21121207900012774b17",
      "created": 1522770562,
      "updated": 1522770564
    },
    {
      "id": "5ac3a279774b170000a40110",
      "text": "",
      "userId": "59fb21121207900012774b17",
      "created": 1522770555,
      "updated": 1522770555
    }
  ]
}