{
  "id": "5b32f220a6b0810014040258",
  "title": "まぐろなボタン",
  "created": 1530065444,
  "updated": 1530065480,
  "lines": [
    {
      "id": "5b32f220a6b0810014040258",
      "text": "まぐろなボタン",
      "userId": "59fb21121207900012774b17",
      "created": 1530065444,
      "updated": 1530065445
    },
    {
      "id": "5b32f225774b170000268507",
      "text": "[マグロナ]のファンによって作られた、声が出る[ボタン]",
      "userId": "59fb21121207900012774b17",
      "created": 1530065445,
      "updated": 1530065470
    },
    {
      "id": "5b32f23f774b170000268509",
      "text": "",
      "userId": "59fb21121207900012774b17",
      "created": 1530065472,
      "updated": 1530065472
    },
    {
      "id": "5b32f228774b170000268508",
      "text": "[まぐろなボタン http://magurona-button.sakura.ne.jp/]",
      "userId": "59fb21121207900012774b17",
      "created": 1530065449,
      "updated": 1530065478
    }
  ]
}