{
  "id": "5b88378bf6f47f0014c765f6",
  "title": "VTuberLand",
  "created": 1535653773,
  "updated": 1563269844,
  "lines": [
    {
      "id": "5b88378bf6f47f0014c765f6",
      "text": "VTuberLand",
      "userId": "59fb21121207900012774b17",
      "created": 1535653773,
      "updated": 1535653775
    },
    {
      "id": "5b88378f774b170000a56bc1",
      "text": "[よみうりランド]で開催される、VTuberのイベント",
      "userId": "59fb21121207900012774b17",
      "created": 1535653776,
      "updated": 1535653794
    },
    {
      "id": "5b8837f7774b170000a56bd4",
      "text": "[.LIVE]と[にじさんじ]に所属するVTuber30組が集結",
      "userId": "59fb21121207900012774b17",
      "created": 1535653879,
      "updated": 1535653899
    },
    {
      "id": "5b88380a774b170000a56bd5",
      "text": "2018年9月19日～23日 .LIVEDays",
      "userId": "59fb21121207900012774b17",
      "created": 1535653899,
      "updated": 1560509286
    },
    {
      "id": "5b883815774b170000a56bd6",
      "text": "2018年9月24日～30日 にじさんじDays",
      "userId": "59fb21121207900012774b17",
      "created": 1535653910,
      "updated": 1560509289
    },
    {
      "id": "5b8837b3774b170000a56bc8",
      "text": "",
      "userId": "59fb21121207900012774b17",
      "created": 1535653811,
      "updated": 1535653811
    },
    {
      "id": "5b8837af774b170000a56bc7",
      "text": "もっと詳しく知りたい",
      "userId": "59fb21121207900012774b17",
      "created": 1535653808,
      "updated": 1535653817
    },
    {
      "id": "5b8837a1774b170000a56bc4",
      "text": " [http://kai-you.net/article/56860 ミライアカリ、電脳少女シロ、月ノ美兎がコラボ 「VtuberLand」開演 - KAI-YOU.net]",
      "userId": "59fb21121207900012774b17",
      "created": 1535653794,
      "updated": 1535653817
    },
    {
      "id": "5d037b7c0db335000040d2e2",
      "text": " [https://tieup.tokyo/vtuberland/ VTuberLand！よみうりランドで開園決定！]",
      "userId": "5a4296f4464d9800140db335",
      "created": 1560509304,
      "updated": 1560509329
    },
    {
      "id": "5b8837c3774b170000a56bc9",
      "text": "",
      "userId": "59fb21121207900012774b17",
      "created": 1535653828,
      "updated": 1535653828
    },
    {
      "id": "5b8837c3774b170000a56bca",
      "text": "出演",
      "userId": "59fb21121207900012774b17",
      "created": 1535653828,
      "updated": 1535653830
    },
    {
      "id": "5b8837c7774b170000a56bcb",
      "text": " [シロ]",
      "userId": "59fb21121207900012774b17",
      "created": 1535653832,
      "updated": 1535653833
    },
    {
      "id": "5b8837d9774b170000a56bd0",
      "text": " [ミライアカリ]",
      "userId": "59fb21121207900012774b17",
      "created": 1535653850,
      "updated": 1535653850
    },
    {
      "id": "5b8837ca774b170000a56bcc",
      "text": " [月ノ美兎]",
      "userId": "59fb21121207900012774b17",
      "created": 1535653835,
      "updated": 1535653837
    },
    {
      "id": "5b8837d0774b170000a56bce",
      "text": " [静凛]",
      "userId": "59fb21121207900012774b17",
      "created": 1535653841,
      "updated": 1553398988
    },
    {
      "id": "5b8837d5774b170000a56bcf",
      "text": " [樋口楓]",
      "userId": "59fb21121207900012774b17",
      "created": 1535653846,
      "updated": 1535653848
    },
    {
      "id": "5b8837dc774b170000a56bd1",
      "text": " [猫宮ひなた]",
      "userId": "59fb21121207900012774b17",
      "created": 1535653853,
      "updated": 1535653859
    },
    {
      "id": "5b8837e2774b170000a56bd2",
      "text": " [御来屋 久遠]",
      "userId": "59fb21121207900012774b17",
      "created": 1535653859,
      "updated": 1535653865
    },
    {
      "id": "5b8837ee774b170000a56bd3",
      "text": "ゲリラ出演",
      "userId": "59fb21121207900012774b17",
      "created": 1535653870,
      "updated": 1563269840
    },
    {
      "id": "5d2d9ac10db33500003b68ab",
      "text": "\t[鷹宮リオン]",
      "userId": "5a4296f4464d9800140db335",
      "created": 1563269822,
      "updated": 1563269844
    },
    {
      "id": "5d2d9ac40db33500003b68ac",
      "text": "\t？？？",
      "userId": "5a4296f4464d9800140db335",
      "created": 1563269825,
      "updated": 1563269844
    },
    {
      "id": "5b8837a2774b170000a56bc5",
      "text": "",
      "userId": "59fb21121207900012774b17",
      "created": 1535653794,
      "updated": 1535653794
    },
    {
      "id": "5b8837a1774b170000a56bc3",
      "text": "#リアルイベント",
      "userId": "59fb21121207900012774b17",
      "created": 1535653794,
      "updated": 1535653797
    },
    {
      "id": "5b883791774b170000a56bc2",
      "text": "",
      "userId": "59fb21121207900012774b17",
      "created": 1535653777,
      "updated": 1535653777
    }
  ]
}