{
  "id": "5c2cd4ea9d05bc001758798b",
  "title": "鈴木ヒナ",
  "created": 1546441964,
  "updated": 1569838949,
  "lines": [
    {
      "id": "5c2cd4ea9d05bc001758798b",
      "text": "鈴木ヒナ",
      "userId": "59fb21121207900012774b17",
      "created": 1546441964,
      "updated": 1546441964
    },
    {
      "id": "5c2cd505774b170000435d28",
      "text": "[https://pbs.twimg.com/profile_images/1000273675747143681/x-5yJZjG_400x400.jpg]",
      "userId": "59fb21121207900012774b17",
      "created": 1546441989,
      "updated": 1546441989
    },
    {
      "id": "5c2cd4fa774b170000435d26",
      "text": "",
      "userId": "59fb21121207900012774b17",
      "created": 1546441978,
      "updated": 1546448247
    },
    {
      "id": "5c2ced72774b170000d426b6",
      "text": "要約",
      "userId": "59fb21121207900012774b17",
      "created": 1546448242,
      "updated": 1546448242
    },
    {
      "id": "5c2ced72774b170000d426b8",
      "text": " [田中ヒメ]と一緒に活動している",
      "userId": "59fb21121207900012774b17",
      "created": 1546448242,
      "updated": 1546448296
    },
    {
      "id": "5c2ced72774b170000d426b9",
      "text": "",
      "userId": "59fb21121207900012774b17",
      "created": 1546448242,
      "updated": 1546448242
    },
    {
      "id": "5c2ced72774b170000d426ba",
      "text": "自己紹介動画",
      "userId": "59fb21121207900012774b17",
      "created": 1546448242,
      "updated": 1546448242
    },
    {
      "id": "5c2ced72774b170000d426bb",
      "text": " ",
      "userId": "59fb21121207900012774b17",
      "created": 1546448242,
      "updated": 1567913874
    },
    {
      "id": "5c2ced72774b170000d426bc",
      "text": "",
      "userId": "59fb21121207900012774b17",
      "created": 1546448242,
      "updated": 1546448242
    },
    {
      "id": "5c2ced72774b170000d426bd",
      "text": "もっと詳しく知りたい",
      "userId": "59fb21121207900012774b17",
      "created": 1546448242,
      "updated": 1546448242
    },
    {
      "id": "5c2ced72774b170000d426be",
      "text": " ",
      "userId": "59fb21121207900012774b17",
      "created": 1546448242,
      "updated": 1567913877
    },
    {
      "id": "5c2ced72774b170000d426bf",
      "text": "",
      "userId": "59fb21121207900012774b17",
      "created": 1546448242,
      "updated": 1546448242
    },
    {
      "id": "5c2ced72774b170000d426c0",
      "text": "アカウント",
      "userId": "59fb21121207900012774b17",
      "created": 1546448242,
      "updated": 1546448242
    },
    {
      "id": "5c2ced72774b170000d426c1",
      "text": " [/icons/twitter.icon] https://twitter.com/HinaSuzuki_HH",
      "userId": "59fb21121207900012774b17",
      "created": 1546448242,
      "updated": 1546448250
    },
    {
      "id": "5c2ced72774b170000d426c2",
      "text": " [/icons/youtube.icon] https://www.youtube.com/channel/UCFv2z4iM5vHrS8bZPq4fHQQ",
      "userId": "59fb21121207900012774b17",
      "created": 1546448242,
      "updated": 1546448275
    },
    {
      "id": "5c2ced8a774b170000d426e0",
      "text": " [/icons/niconico.icon] https://www.nicovideo.jp/user/78191728",
      "userId": "59fb21121207900012774b17",
      "created": 1546448266,
      "updated": 1546448266
    },
    {
      "id": "5c2ced72774b170000d426c3",
      "text": "",
      "userId": "59fb21121207900012774b17",
      "created": 1546448242,
      "updated": 1569838949
    },
    {
      "id": "5c2ced72774b170000d426c9",
      "text": "",
      "userId": "59fb21121207900012774b17",
      "created": 1546448242,
      "updated": 1546448242
    },
    {
      "id": "5c2ced72774b170000d426ca",
      "text": "語録",
      "userId": "59fb21121207900012774b17",
      "created": 1546448242,
      "updated": 1546448242
    },
    {
      "id": "5c2ced72774b170000d426cb",
      "text": " ",
      "userId": "59fb21121207900012774b17",
      "created": 1546448242,
      "updated": 1567913882
    },
    {
      "id": "5c2ced72774b170000d426cf",
      "text": "",
      "userId": "59fb21121207900012774b17",
      "created": 1546448242,
      "updated": 1546448242
    },
    {
      "id": "5c2ced72774b170000d426d0",
      "text": "基本情報",
      "userId": "59fb21121207900012774b17",
      "created": 1546448242,
      "updated": 1546448242
    },
    {
      "id": "5c2ced72774b170000d426d1",
      "text": " 視聴者のよびかた：",
      "userId": "59fb21121207900012774b17",
      "created": 1546448242,
      "updated": 1546448242
    },
    {
      "id": "5c2ced72774b170000d426d2",
      "text": " 名前の読み方：",
      "userId": "59fb21121207900012774b17",
      "created": 1546448242,
      "updated": 1546448242
    },
    {
      "id": "5c2ced72774b170000d426d3",
      "text": " ハッシュタグ：",
      "userId": "59fb21121207900012774b17",
      "created": 1546448242,
      "updated": 1567913884
    },
    {
      "id": "5c2ced72774b170000d426d4",
      "text": " https://himehina.jp/",
      "userId": "59fb21121207900012774b17",
      "created": 1546448242,
      "updated": 1567913956
    },
    {
      "id": "5c2ced72774b170000d426d5",
      "text": "",
      "userId": "59fb21121207900012774b17",
      "created": 1546448242,
      "updated": 1546448242
    },
    {
      "id": "5c2ced72774b170000d426d6",
      "text": "特記事項",
      "userId": "59fb21121207900012774b17",
      "created": 1546448242,
      "updated": 1546448242
    },
    {
      "id": "5c2ced72774b170000d426d7",
      "text": "",
      "userId": "59fb21121207900012774b17",
      "created": 1546448242,
      "updated": 1546448242
    },
    {
      "id": "5c2ced72774b170000d426d8",
      "text": "生みの親",
      "userId": "59fb21121207900012774b17",
      "created": 1546448242,
      "updated": 1546448242
    },
    {
      "id": "5c2ced72774b170000d426d9",
      "text": " キャラクターデザイン：[しゅがお]",
      "userId": "59fb21121207900012774b17",
      "created": 1546448242,
      "updated": 1547052958
    },
    {
      "id": "5c2ced72774b170000d426da",
      "text": "",
      "userId": "59fb21121207900012774b17",
      "created": 1546448242,
      "updated": 1546448242
    },
    {
      "id": "5c2ced72774b170000d426db",
      "text": "#バーチャルYouTuber",
      "userId": "59fb21121207900012774b17",
      "created": 1546448242,
      "updated": 1546448242
    },
    {
      "id": "5c2ced72774b170000d426dc",
      "text": "#ヒメヒナ",
      "userId": "59fb21121207900012774b17",
      "created": 1546448242,
      "updated": 1567913931
    },
    {
      "id": "5d7477cc0db3350000649c4e",
      "text": "",
      "userId": "5a4296f4464d9800140db335",
      "created": 1567913930,
      "updated": 1567913930
    }
  ]
}