{
  "id": "5c2dc14c001da5001787f4a3",
  "title": "ぱりぷろ",
  "created": 1546502479,
  "updated": 1555214594,
  "lines": [
    {
      "id": "5c2dc14c001da5001787f4a3",
      "text": "ぱりぷろ",
      "userId": "5a4296f4464d9800140db335",
      "created": 1546502479,
      "updated": 1546502481
    },
    {
      "id": "5c2dc1520db33500008fe67e",
      "text": "",
      "userId": "5a4296f4464d9800140db335",
      "created": 1546502482,
      "updated": 1546502524
    },
    {
      "id": "5c2dc17f0db33500008fe681",
      "text": "要約",
      "userId": "5a4296f4464d9800140db335",
      "created": 1546502527,
      "updated": 1546502528
    },
    {
      "id": "5c2dc15b0db33500008fe680",
      "text": "　イラストレーター [Paryi] によるVTuberプロジェクト「[Project Paryi]」の一環で発足したグループ「ぱりぷろ」",
      "userId": "5a4296f4464d9800140db335",
      "created": 1546502491,
      "updated": 1546502544
    },
    {
      "id": "5cb059cb0db335000026c92c",
      "text": "　2019年4月までグループとして活動していた。その後個別に個人として活動することに。",
      "userId": "5a4296f4464d9800140db335",
      "created": 1555061191,
      "updated": 1555061215
    },
    {
      "id": "5cb059e40db335000026c92d",
      "text": "　\thttps://twitter.com/par1y/status/1116613307870244864",
      "userId": "5a4296f4464d9800140db335",
      "created": 1555061215,
      "updated": 1555061216
    },
    {
      "id": "5c2dc15a0db33500008fe67f",
      "text": "",
      "userId": "5a4296f4464d9800140db335",
      "created": 1546502490,
      "updated": 1546502490
    },
    {
      "id": "5c2dc1a70db33500008fe682",
      "text": "メンバー",
      "userId": "5a4296f4464d9800140db335",
      "created": 1546502567,
      "updated": 1546502569
    },
    {
      "id": "5c2dc1a90db33500008fe684",
      "text": "　[ユメノシオリ]",
      "userId": "5a4296f4464d9800140db335",
      "created": 1546502569,
      "updated": 1546502584
    },
    {
      "id": "5c2dc1ae0db33500008fe685",
      "text": "　[神楽めあ]",
      "userId": "5a4296f4464d9800140db335",
      "created": 1546502574,
      "updated": 1546502586
    },
    {
      "id": "5c2dc1b00db33500008fe686",
      "text": "　[千草はな]",
      "userId": "5a4296f4464d9800140db335",
      "created": 1546502576,
      "updated": 1546502588
    },
    {
      "id": "5c2dc1b40db33500008fe687",
      "text": " [森永みう]",
      "userId": "5a4296f4464d9800140db335",
      "created": 1546502580,
      "updated": 1546502590
    },
    {
      "id": "5c2dc1b40db33500008fe688",
      "text": " [有栖マナ]",
      "userId": "5a4296f4464d9800140db335",
      "created": 1546502580,
      "updated": 1546502592
    },
    {
      "id": "5c2dc1b40db33500008fe689",
      "text": " [高槻りつ]",
      "userId": "5a4296f4464d9800140db335",
      "created": 1546502580,
      "updated": 1546502593
    },
    {
      "id": "5c2dc1b40db33500008fe68a",
      "text": " [花園セレナ]",
      "userId": "5a4296f4464d9800140db335",
      "created": 1546502580,
      "updated": 1546502595
    },
    {
      "id": "5c2dc1b40db33500008fe68b",
      "text": " [ENA]",
      "userId": "5a4296f4464d9800140db335",
      "created": 1546502580,
      "updated": 1546502596
    },
    {
      "id": "5c2dc1a90db33500008fe683",
      "text": "",
      "userId": "5a4296f4464d9800140db335",
      "created": 1546502569,
      "updated": 1546502569
    },
    {
      "id": "5c2dc1c60db33500008fe68d",
      "text": "もっと詳しく知りたい",
      "userId": "5a4296f4464d9800140db335",
      "created": 1546502598,
      "updated": 1546502601
    },
    {
      "id": "5cb05a9d0db335000026c936",
      "text": "　[https://dic.pixiv.net/a/%E3%81%B1%E3%82%8A%E3%81%B7%E3%82%8D ぱりぷろ] -- ピクシブ百科事典",
      "userId": "5a4296f4464d9800140db335",
      "created": 1555061400,
      "updated": 1555061400
    },
    {
      "id": "5c2dc1c90db33500008fe68e",
      "text": "　非公式wiki [- https://seesaawiki.jp/project_paryi/]",
      "userId": "5a4296f4464d9800140db335",
      "created": 1546502601,
      "updated": 1555061160
    },
    {
      "id": "5cb059af0db335000026c92b",
      "text": "　\t消滅。2019年1月にはアクセスできなくなっていた模様です。",
      "userId": "5a4296f4464d9800140db335",
      "created": 1555061162,
      "updated": 1555061405
    },
    {
      "id": "5c2dc1c50db33500008fe68c",
      "text": "",
      "userId": "5a4296f4464d9800140db335",
      "created": 1546502597,
      "updated": 1546502597
    },
    {
      "id": "5cb05a570db335000026c934",
      "text": "#VTuberグループ",
      "userId": "5a4296f4464d9800140db335",
      "created": 1555061330,
      "updated": 1555061333
    },
    {
      "id": "5cb05a570db335000026c935",
      "text": "",
      "userId": "5a4296f4464d9800140db335",
      "created": 1555061330,
      "updated": 1555061330
    }
  ]
}