{
  "id": "5c3627b0862d7300172dcece",
  "title": "LITA",
  "created": 1547052983,
  "updated": 1609234970,
  "lines": [
    {
      "id": "5c3627b0862d7300172dcece",
      "text": "LITA",
      "userId": "59fb21121207900012774b17",
      "created": 1547052983,
      "updated": 1547052983
    },
    {
      "id": "5c5b1b2f774b1700006631ba",
      "text": "[https://pbs.twimg.com/profile_images/1004640804994859009/-2iVZRGm_400x400.jpg]",
      "userId": "59fb21121207900012774b17",
      "created": 1549474607,
      "updated": 1549474607
    },
    {
      "id": "5c5b1b2f774b1700006631bb",
      "text": "",
      "userId": "59fb21121207900012774b17",
      "created": 1549474607,
      "updated": 1549474607
    },
    {
      "id": "5c5b1b12774b170000663190",
      "text": "要約",
      "userId": "59fb21121207900012774b17",
      "created": 1549474578,
      "updated": 1549474578
    },
    {
      "id": "5c5b1b12774b170000663191",
      "text": " [KMNZ]",
      "userId": "59fb21121207900012774b17",
      "created": 1549474578,
      "updated": 1558095052
    },
    {
      "id": "5c5b1b12774b170000663193",
      "text": "",
      "userId": "59fb21121207900012774b17",
      "created": 1549474578,
      "updated": 1549474578
    },
    {
      "id": "5c5b1b12774b170000663194",
      "text": "自己紹介動画",
      "userId": "59fb21121207900012774b17",
      "created": 1549474578,
      "updated": 1549474578
    },
    {
      "id": "5c5b1b12774b170000663195",
      "text": " ",
      "userId": "59fb21121207900012774b17",
      "created": 1549474578,
      "updated": 1609234948
    },
    {
      "id": "5c5b1b12774b170000663196",
      "text": "",
      "userId": "59fb21121207900012774b17",
      "created": 1549474578,
      "updated": 1549474578
    },
    {
      "id": "5c5b1b12774b170000663197",
      "text": "もっと詳しく知りたい",
      "userId": "59fb21121207900012774b17",
      "created": 1549474578,
      "updated": 1549474578
    },
    {
      "id": "5c5b1b12774b170000663198",
      "text": " ",
      "userId": "59fb21121207900012774b17",
      "created": 1549474578,
      "updated": 1609234950
    },
    {
      "id": "5c5b1b12774b170000663199",
      "text": "",
      "userId": "59fb21121207900012774b17",
      "created": 1549474578,
      "updated": 1549474578
    },
    {
      "id": "5c5b1b12774b17000066319a",
      "text": "アカウント",
      "userId": "59fb21121207900012774b17",
      "created": 1549474578,
      "updated": 1549474578
    },
    {
      "id": "5c5b1b12774b17000066319b",
      "text": " [/icons/twitter.icon] https://twitter.com/kmnzlita",
      "userId": "59fb21121207900012774b17",
      "created": 1549474578,
      "updated": 1549474615
    },
    {
      "id": "5c5b1b12774b17000066319c",
      "text": " [/icons/youtube.icon] https://www.youtube.com/channel/UCwuS0uY-Z2Gr_5OV2oFybFA",
      "userId": "59fb21121207900012774b17",
      "created": 1549474578,
      "updated": 1549474638
    },
    {
      "id": "5c5b1bb6774b1700006631be",
      "text": " [/icons/bilibili.icon] http://vc.bilibili.com/video/2057809",
      "userId": "59fb21121207900012774b17",
      "created": 1549474743,
      "updated": 1549474743
    },
    {
      "id": "5c5b1b12774b17000066319d",
      "text": "",
      "userId": "59fb21121207900012774b17",
      "created": 1549474578,
      "updated": 1576687312
    },
    {
      "id": "5c5b1b12774b1700006631a4",
      "text": "",
      "userId": "59fb21121207900012774b17",
      "created": 1549474578,
      "updated": 1549474578
    },
    {
      "id": "5c5b1b12774b1700006631a5",
      "text": "語録",
      "userId": "59fb21121207900012774b17",
      "created": 1549474578,
      "updated": 1549474578
    },
    {
      "id": "5c5b1b12774b1700006631a6",
      "text": " ",
      "userId": "59fb21121207900012774b17",
      "created": 1549474578,
      "updated": 1609234957
    },
    {
      "id": "5c5b1b12774b1700006631aa",
      "text": "",
      "userId": "59fb21121207900012774b17",
      "created": 1549474578,
      "updated": 1549474578
    },
    {
      "id": "5c5b1b12774b1700006631ab",
      "text": "基本情報",
      "userId": "59fb21121207900012774b17",
      "created": 1549474578,
      "updated": 1549474578
    },
    {
      "id": "5c5b1b12774b1700006631ac",
      "text": " 視聴者のよびかた：りた",
      "userId": "59fb21121207900012774b17",
      "created": 1549474578,
      "updated": 1558095066
    },
    {
      "id": "5c5b1b12774b1700006631ad",
      "text": " 名前の読み方：",
      "userId": "59fb21121207900012774b17",
      "created": 1549474578,
      "updated": 1549474578
    },
    {
      "id": "5c5b1b12774b1700006631ae",
      "text": " ハッシュタグ：",
      "userId": "59fb21121207900012774b17",
      "created": 1549474578,
      "updated": 1609234959
    },
    {
      "id": "5c5b1b12774b1700006631af",
      "text": " ",
      "userId": "59fb21121207900012774b17",
      "created": 1549474578,
      "updated": 1609234961
    },
    {
      "id": "5c5b1b12774b1700006631b0",
      "text": "",
      "userId": "59fb21121207900012774b17",
      "created": 1549474578,
      "updated": 1549474578
    },
    {
      "id": "5c5b1b12774b1700006631b1",
      "text": "特記事項",
      "userId": "59fb21121207900012774b17",
      "created": 1549474578,
      "updated": 1549474578
    },
    {
      "id": "5cdea4e2774b1700004d6261",
      "text": " 中高6年間は[演劇部]に所属していた",
      "userId": "59fb21121207900012774b17",
      "created": 1558095075,
      "updated": 1558095098
    },
    {
      "id": "5c5b1b12774b1700006631b2",
      "text": "  [ぶいおん!!] ep.05",
      "userId": "59fb21121207900012774b17",
      "created": 1549474578,
      "updated": 1558095233
    },
    {
      "id": "5feafa160db33500008f06d7",
      "text": "",
      "userId": "5a4296f4464d9800140db335",
      "created": 1609234964,
      "updated": 1609234964
    },
    {
      "id": "5c5b1b12774b1700006631b3",
      "text": "生みの親",
      "userId": "59fb21121207900012774b17",
      "created": 1549474578,
      "updated": 1549474578
    },
    {
      "id": "5c5b1b19774b1700006631b8",
      "text": " キャラクターデザイン：[しゅがお]",
      "userId": "59fb21121207900012774b17",
      "created": 1549474585,
      "updated": 1549474586
    },
    {
      "id": "5c5b1b12774b1700006631b4",
      "text": "",
      "userId": "59fb21121207900012774b17",
      "created": 1549474578,
      "updated": 1549474588
    },
    {
      "id": "5c5b1b12774b1700006631b5",
      "text": "",
      "userId": "59fb21121207900012774b17",
      "created": 1549474578,
      "updated": 1549474578
    },
    {
      "id": "5c5b1b12774b1700006631b6",
      "text": "#バーチャルYouTuber",
      "userId": "59fb21121207900012774b17",
      "created": 1549474578,
      "updated": 1549474578
    },
    {
      "id": "5c5b1b12774b1700006631b7",
      "text": "",
      "userId": "59fb21121207900012774b17",
      "created": 1549474578,
      "updated": 1549474578
    }
  ]
}