{
  "id": "5cffd922eaa6470017dd6789",
  "title": "雨森小夜、17歳になる",
  "created": 1560271146,
  "updated": 1560271249,
  "lines": [
    {
      "id": "5cffd922eaa6470017dd6789",
      "text": "雨森小夜、17歳になる",
      "userId": "59fb21121207900012774b17",
      "created": 1560271146,
      "updated": 1560271163
    },
    {
      "id": "5cffd98a774b1700006a44e7",
      "text": "2018年6月11日",
      "userId": "59fb21121207900012774b17",
      "created": 1560271242,
      "updated": 1560271249
    },
    {
      "id": "5cffd940774b1700006a44e3",
      "text": "[雨森小夜]さん（１７）が誕生日を迎え、17歳になった",
      "userId": "59fb21121207900012774b17",
      "created": 1560271168,
      "updated": 1560271225
    },
    {
      "id": "5cffd940774b1700006a44e4",
      "text": "https://twitter.com/sayo_amemori/status/1138216405768318976?s=21",
      "userId": "59fb21121207900012774b17",
      "created": 1560271168,
      "updated": 1560271172
    },
    {
      "id": "5cffd944774b1700006a44e5",
      "text": "",
      "userId": "59fb21121207900012774b17",
      "created": 1560271172,
      "updated": 1560271172
    }
  ]
}