{
  "id": "5d7657b322094e0017533d3c",
  "title": "イイカンジ！！",
  "created": 1568036792,
  "updated": 1568271272,
  "lines": [
    {
      "id": "5d7657b322094e0017533d3c",
      "text": "イイカンジ！！",
      "userId": "5a4296f4464d9800140db335",
      "created": 1568036792,
      "updated": 1568036792
    },
    {
      "id": "5d7657b90db3350000d74ecb",
      "text": "[https://www.youtube.com/watch?v=NFynHunb5fI]",
      "userId": "5a4296f4464d9800140db335",
      "created": 1568036792,
      "updated": 1568036796
    },
    {
      "id": "5d7657bc0db3350000d74ecd",
      "text": "",
      "userId": "5a4296f4464d9800140db335",
      "created": 1568036796,
      "updated": 1568036796
    },
    {
      "id": "5d7657c00db3350000d74ece",
      "text": "　2019年6月に公開された、[ルキロキ]の2ndオリジナル曲。",
      "userId": "5a4296f4464d9800140db335",
      "created": 1568036800,
      "updated": 1568036823
    },
    {
      "id": "5d7657d70db3350000d74ecf",
      "text": "　関係者",
      "userId": "5a4296f4464d9800140db335",
      "created": 1568036823,
      "updated": 1568036825
    },
    {
      "id": "5d7657d90db3350000d74ed0",
      "text": "　\t作詞・作曲：[キノシタ]",
      "userId": "5a4296f4464d9800140db335",
      "created": 1568036825,
      "updated": 1568036862
    },
    {
      "id": "5d7657e20db3350000d74ed1",
      "text": "　\t振付・ダンス指導：[ATY]（[明香里]、[夕香里]）",
      "userId": "5a4296f4464d9800140db335",
      "created": 1568036834,
      "updated": 1568036878
    },
    {
      "id": "5d7657e80db3350000d74ed2",
      "text": "　\tボーカル：[流石乃ルキ]、[流石乃ロキ]",
      "userId": "5a4296f4464d9800140db335",
      "created": 1568036840,
      "updated": 1568036883
    },
    {
      "id": "5d7657fa0db3350000d74ed4",
      "text": "　\t動画：[3tuiro]",
      "userId": "5a4296f4464d9800140db335",
      "created": 1568036859,
      "updated": 1568036923
    },
    {
      "id": "5d7657fa0db3350000d74ed5",
      "text": "  ライブデザイナー：[Lizardo]",
      "userId": "5a4296f4464d9800140db335",
      "created": 1568036859,
      "updated": 1568036921
    },
    {
      "id": "5d7657fa0db3350000d74ed6",
      "text": "  ミックス： [西本康佑]",
      "userId": "5a4296f4464d9800140db335",
      "created": 1568036859,
      "updated": 1568036919
    },
    {
      "id": "5d7657fa0db3350000d74ed7",
      "text": "  イラスト：[曜大]",
      "userId": "5a4296f4464d9800140db335",
      "created": 1568036859,
      "updated": 1568036917
    },
    {
      "id": "5d7657fa0db3350000d74ed8",
      "text": "  システムエンジニア：[fsyuu]",
      "userId": "5a4296f4464d9800140db335",
      "created": 1568036859,
      "updated": 1568036916
    },
    {
      "id": "5d76587d0db3350000d74edb",
      "text": " 告知",
      "userId": "5a4296f4464d9800140db335",
      "created": 1568036989,
      "updated": 1568036992
    },
    {
      "id": "5d7657bc0db3350000d74ecc",
      "text": "\t [https://www.youtube.com/watch?v=WAFBfrfEQcA]",
      "userId": "5a4296f4464d9800140db335",
      "created": 1568036796,
      "updated": 1568036992
    },
    {
      "id": "5d7658790db3350000d74eda",
      "text": "",
      "userId": "5a4296f4464d9800140db335",
      "created": 1568036985,
      "updated": 1568036985
    },
    {
      "id": "5d7658780db3350000d74ed9",
      "text": "#オリジナル楽曲 #ルキロキの曲",
      "userId": "5a4296f4464d9800140db335",
      "created": 1568036984,
      "updated": 1568271272
    },
    {
      "id": "5d79eba70db33500004d9dd0",
      "text": "",
      "userId": "5a4296f4464d9800140db335",
      "created": 1568271271,
      "updated": 1568271271
    }
  ]
}