{
  "id": "6002ce39952a7a001c217ace",
  "title": "グジュ",
  "created": 1610796602,
  "updated": 1610796630,
  "lines": [
    {
      "id": "6002ce39952a7a001c217ace",
      "text": "グジュ",
      "userId": "5a4296f4464d9800140db335",
      "created": 1610796602,
      "updated": 1610796605
    },
    {
      "id": "6002ce400db33500006ed6a6",
      "text": "",
      "userId": "5a4296f4464d9800140db335",
      "created": 1610796605,
      "updated": 1610796605
    },
    {
      "id": "6002ce400db33500006ed6a7",
      "text": "→ [グリーンルージュ]",
      "userId": "5a4296f4464d9800140db335",
      "created": 1610796605,
      "updated": 1610796608
    },
    {
      "id": "6002ce410db33500006ed6a8",
      "text": "",
      "userId": "5a4296f4464d9800140db335",
      "created": 1610796606,
      "updated": 1610796606
    },
    {
      "id": "6002ce460db33500006ed6a9",
      "text": "（2021年1月のライブ「[Virtual Baiser]」での用語）",
      "userId": "5a4296f4464d9800140db335",
      "created": 1610796611,
      "updated": 1610796630
    },
    {
      "id": "6002ce480db33500006ed6aa",
      "text": "",
      "userId": "5a4296f4464d9800140db335",
      "created": 1610796613,
      "updated": 1610796613
    }
  ]
}