{
  "id": "67c6cdd8dfe57d5f10c72a87",
  "title": "萌実リニューアル衣装お披露目",
  "created": 1741082078,
  "updated": 1741082152,
  "lines": [
    {
      "id": "67c6cdd8dfe57d5f10c72a87",
      "text": "萌実リニューアル衣装お披露目",
      "userId": "5f0e769da385ed001ecc1fc1",
      "created": 1741082078,
      "updated": 1741082106
    },
    {
      "id": "67c6cde8cc1fc1000030b509",
      "text": "[https://www.youtube.com/live/IgXPD3R5L50?si=pldm5dqQ4Y0OK7CI]",
      "userId": "5f0e769da385ed001ecc1fc1",
      "created": 1741082088,
      "updated": 1741082090
    },
    {
      "id": "67c6cdeacc1fc1000030b50b",
      "text": "",
      "userId": "5f0e769da385ed001ecc1fc1",
      "created": 1741082090,
      "updated": 1741082090
    },
    {
      "id": "67c6cdeacc1fc1000030b50a",
      "text": "配信日　2025/03/05",
      "userId": "5f0e769da385ed001ecc1fc1",
      "created": 1741082090,
      "updated": 1741082131
    },
    {
      "id": "67c6ce0dcc1fc1000030b50c",
      "text": "",
      "userId": "5f0e769da385ed001ecc1fc1",
      "created": 1741082125,
      "updated": 1741082125
    },
    {
      "id": "67c6ce19cc1fc1000030b50d",
      "text": "[萌実]がリニューアル衣装をお披露目",
      "userId": "5f0e769da385ed001ecc1fc1",
      "created": 1741082137,
      "updated": 1741082152
    },
    {
      "id": "67c6ce1bcc1fc1000030b50e",
      "text": "",
      "userId": "5f0e769da385ed001ecc1fc1",
      "created": 1741082139,
      "updated": 1741082139
    }
  ]
}