{
  "id": "6804c6b3f70e187d9d3ba594",
  "title": "生返るるる生き返る",
  "created": 1745143476,
  "updated": 1745143576,
  "lines": [
    {
      "id": "6804c6b3f70e187d9d3ba594",
      "text": "生返るるる生き返る",
      "userId": "5f0e769da385ed001ecc1fc1",
      "created": 1745143476,
      "updated": 1745143480
    },
    {
      "id": "6804c6b90000000000cf8344",
      "text": "2025/4/17に[生返るるる]が活動再開を発表した。",
      "userId": "5f0e769da385ed001ecc1fc1",
      "created": 1745143481,
      "updated": 1745143500
    },
    {
      "id": "6804c6bf0000000000cf8345",
      "text": "[https://www.youtube.com/watch?v=eSMNV482Xg4]",
      "userId": "5f0e769da385ed001ecc1fc1",
      "created": 1745143487,
      "updated": 1745143572
    },
    {
      "id": "6804c7130000000000cf8346",
      "text": "",
      "userId": "5f0e769da385ed001ecc1fc1",
      "created": 1745143572,
      "updated": 1745143572
    }
  ]
}